{
  "manifestVersion": "3.2",
  "admin": {
    "address": "0x338b1f296217485bf4df6CE9f93ab4C73F72b57D",
    "txHash": "0x88947239d932c76cdb60a674ea0823e300dced3fbb280e2da2f61db9d1da0a19"
  },
  "proxies": [
    {
      "address": "0x8e0B46ec3B95c81355175693dA0083b00fCc1326",
      "txHash": "0x823b2e0bc420d3049ab46057e72eef6651a3a0bc61996d38646d633176409b3e",
      "kind": "transparent"
    }
  ],
  "impls": {
    "2637682cead402c6d7bdae5a62ba3e83abd319dd41c2827e6d2f76b13b0b6700": {
      "address": "0xe87eFc02F26EFE45171afDBEc85D743FDB2Eb1FB",
      "txHash": "0x7783fb5b7efe0fe5a0bab6b603118f8c27cc92f2ac192b9064e7b3335b48a39a",
      "layout": {
        "storage": [
          {
            "label": "initialized",
            "offset": 0,
            "slot": "0",
            "type": "t_bool",
            "contract": "UnlockInitializable",
            "src": "contracts/utils/UnlockInitializable.sol:39"
          },
          {
            "label": "initializing",
            "offset": 1,
            "slot": "0",
            "type": "t_bool",
            "contract": "UnlockInitializable",
            "src": "contracts/utils/UnlockInitializable.sol:44"
          },
          {
            "label": "______gap",
            "offset": 0,
            "slot": "1",
            "type": "t_array(t_uint256)50_storage",
            "contract": "UnlockContextUpgradeable",
            "src": "contracts/utils/UnlockContextUpgradeable.sol:47"
          },
          {
            "label": "_owner",
            "offset": 0,
            "slot": "51",
            "type": "t_address",
            "contract": "UnlockOwnable",
            "src": "contracts/utils/UnlockOwnable.sol:26"
          },
          {
            "label": "______gap",
            "offset": 0,
            "slot": "52",
            "type": "t_array(t_uint256)50_storage",
            "contract": "UnlockOwnable",
            "src": "contracts/utils/UnlockOwnable.sol:96"
          },
          {
            "label": "grossNetworkProduct",
            "offset": 0,
            "slot": "102",
            "type": "t_uint256",
            "contract": "Unlock",
            "src": "contracts/Unlock.sol:61"
          },
          {
            "label": "totalDiscountGranted",
            "offset": 0,
            "slot": "103",
            "type": "t_uint256",
            "contract": "Unlock",
            "src": "contracts/Unlock.sol:63"
          },
          {
            "label": "locks",
            "offset": 0,
            "slot": "104",
            "type": "t_mapping(t_address,t_struct(LockBalances)9608_storage)",
            "contract": "Unlock",
            "src": "contracts/Unlock.sol:66"
          },
          {
            "label": "globalBaseTokenURI",
            "offset": 0,
            "slot": "105",
            "type": "t_string_storage",
            "contract": "Unlock",
            "src": "contracts/Unlock.sol:70"
          },
          {
            "label": "globalTokenSymbol",
            "offset": 0,
            "slot": "106",
            "type": "t_string_storage",
            "contract": "Unlock",
            "src": "contracts/Unlock.sol:74"
          },
          {
            "label": "publicLockAddress",
            "offset": 0,
            "slot": "107",
            "type": "t_address",
            "contract": "Unlock",
            "src": "contracts/Unlock.sol:77"
          },
          {
            "label": "uniswapOracles",
            "offset": 0,
            "slot": "108",
            "type": "t_mapping(t_address,t_contract(IUniswapOracle)25725)",
            "contract": "Unlock",
            "src": "contracts/Unlock.sol:81"
          },
          {
            "label": "weth",
            "offset": 0,
            "slot": "109",
            "type": "t_address",
            "contract": "Unlock",
            "src": "contracts/Unlock.sol:84"
          },
          {
            "label": "udt",
            "offset": 0,
            "slot": "110",
            "type": "t_address",
            "contract": "Unlock",
            "src": "contracts/Unlock.sol:87"
          },
          {
            "label": "estimatedGasForPurchase",
            "offset": 0,
            "slot": "111",
            "type": "t_uint256",
            "contract": "Unlock",
            "src": "contracts/Unlock.sol:90"
          },
          {
            "label": "chainId",
            "offset": 0,
            "slot": "112",
            "type": "t_uint256",
            "contract": "Unlock",
            "src": "contracts/Unlock.sol:93"
          },
          {
            "label": "proxyAdminAddress",
            "offset": 0,
            "slot": "113",
            "type": "t_address",
            "contract": "Unlock",
            "src": "contracts/Unlock.sol:96"
          },
          {
            "label": "proxyAdmin",
            "offset": 0,
            "slot": "114",
            "type": "t_contract(ProxyAdmin)3936",
            "contract": "Unlock",
            "src": "contracts/Unlock.sol:97"
          },
          {
            "label": "_publicLockVersions",
            "offset": 0,
            "slot": "115",
            "type": "t_mapping(t_address,t_uint16)",
            "contract": "Unlock",
            "src": "contracts/Unlock.sol:100"
          },
          {
            "label": "_publicLockImpls",
            "offset": 0,
            "slot": "116",
            "type": "t_mapping(t_uint16,t_address)",
            "contract": "Unlock",
            "src": "contracts/Unlock.sol:101"
          },
          {
            "label": "publicLockLatestVersion",
            "offset": 0,
            "slot": "117",
            "type": "t_uint16",
            "contract": "Unlock",
            "src": "contracts/Unlock.sol:102"
          },
          {
            "label": "permit2",
            "offset": 2,
            "slot": "117",
            "type": "t_address",
            "contract": "Unlock",
            "src": "contracts/Unlock.sol:105"
          }
        ],
        "types": {
          "t_address": {
            "label": "address",
            "numberOfBytes": "20"
          },
          "t_array(t_uint256)50_storage": {
            "label": "uint256[50]",
            "numberOfBytes": "1600"
          },
          "t_bool": {
            "label": "bool",
            "numberOfBytes": "1"
          },
          "t_contract(IUniswapOracle)25725": {
            "label": "contract IUniswapOracle",
            "numberOfBytes": "20"
          },
          "t_contract(ProxyAdmin)3936": {
            "label": "contract ProxyAdmin",
            "numberOfBytes": "20"
          },
          "t_mapping(t_address,t_contract(IUniswapOracle)25725)": {
            "label": "mapping(address => contract IUniswapOracle)",
            "numberOfBytes": "32"
          },
          "t_mapping(t_address,t_struct(LockBalances)9608_storage)": {
            "label": "mapping(address => struct Unlock.LockBalances)",
            "numberOfBytes": "32"
          },
          "t_mapping(t_address,t_uint16)": {
            "label": "mapping(address => uint16)",
            "numberOfBytes": "32"
          },
          "t_mapping(t_uint16,t_address)": {
            "label": "mapping(uint16 => address)",
            "numberOfBytes": "32"
          },
          "t_string_storage": {
            "label": "string",
            "numberOfBytes": "32"
          },
          "t_struct(LockBalances)9608_storage": {
            "label": "struct Unlock.LockBalances",
            "members": [
              {
                "label": "deployed",
                "type": "t_bool",
                "offset": 0,
                "slot": "0"
              },
              {
                "label": "totalSales",
                "type": "t_uint256",
                "offset": 0,
                "slot": "1"
              },
              {
                "label": "yieldedDiscountTokens",
                "type": "t_uint256",
                "offset": 0,
                "slot": "2"
              }
            ],
            "numberOfBytes": "96"
          },
          "t_uint16": {
            "label": "uint16",
            "numberOfBytes": "2"
          },
          "t_uint256": {
            "label": "uint256",
            "numberOfBytes": "32"
          }
        }
      }
    }
  }
}
