{
  "language": "Solidity",
  "sources": {
    "contracts/Migrations.sol": {
      "content": "pragma solidity 0.5.17;\n\n\ncontract Migrations {\n  address public owner;\n  uint public lastCompletedMigration;\n\n  modifier restricted() {\n    if (msg.sender == owner) _;\n  }\n\n  constructor() public {\n    owner = msg.sender;\n  }\n\n  function setCompleted(uint completed) public restricted {\n    lastCompletedMigration = completed;\n  }\n\n  function upgrade(address newAddress) public restricted {\n    Migrations upgraded = Migrations(newAddress);\n    upgraded.setCompleted(lastCompletedMigration);\n  }\n}\n"
    }
  },
  "settings": {
    "optimizer": {
      "enabled": true,
      "runs": 200
    },
    "outputSelection": {
      "*": {
        "*": [
          "abi",
          "evm.bytecode",
          "evm.deployedBytecode",
          "evm.methodIdentifiers",
          "metadata",
          "devdoc",
          "userdoc",
          "storageLayout",
          "evm.gasEstimates"
        ],
        "": [
          "ast"
        ]
      }
    },
    "metadata": {
      "useLiteralContent": true
    }
  }
}